tg_tool/__init__.py
tg_tool/main.py
tg_tool-0.4.4.dist-info/entry_points.txt
tg_tool-0.4.4.dist-info/WHEEL
tg_tool-0.4.4.dist-info/METADATA
tg_tool-0.4.4.dist-info/RECORD
