Metadata-Version: 2.1
Name: tg-tool
Version: 0.4.4
Summary: 
Author: sellercoder
Author-email: veniamin4e@gmail.com
Requires-Python: >=3.7,<4.0
Classifier: Programming Language :: Python :: 3
Classifier: Programming Language :: Python :: 3.7
Classifier: Programming Language :: Python :: 3.8
Requires-Dist: typer (>=0.3.2,<0.4.0)
